pytool/__init__.py
pytool/cmd.py
pytool/json.py
pytool/lang.py
pytool/proxy.py
pytool/text.py
pytool/time.py
pytool-6.0.2.dist-info/licenses/LICENSE.md
pytool-6.0.2.dist-info/METADATA
pytool-6.0.2.dist-info/WHEEL
pytool-6.0.2.dist-info/top_level.txt
pytool-6.0.2.dist-info/RECORD
