Metadata-Version: 2.4
Name: pytool
Version: 6.0.2
Summary: Pytool is a collection of utilities and language enhancements for Python
Author-email: Jacob Alheid <shakefu@gmail.com>
License-Expression: MIT
Requires-Python: <4.0,>=3.9
License-File: LICENSE.md
Requires-Dist: simplejson<4.0.0,>=3.19.2
Dynamic: license-file
